dcm2dir/__init__.py
dcm2dir/dcm2dir.py
dcm2dir/anonymize/__init__.py
dcm2dir/anonymize/anonymize.py
dcm2dir/anonymize/default_anon_config.py
dcm2dir-1.1.0.20250402.dist-info/METADATA
dcm2dir-1.1.0.20250402.dist-info/WHEEL
dcm2dir-1.1.0.20250402.dist-info/entry_points.txt
dcm2dir-1.1.0.20250402.dist-info/licenses/LICENSE
dcm2dir-1.1.0.20250402.dist-info/RECORD
