Metadata-Version: 2.4
Name: dcm2dir
Version: 1.1.0.20250402
Summary: dcm2dir: Organize DICOM files into a structured output folder.
Project-URL: Homepage, https://github.com/HoenikkerPerez/dcm2dir
Author-email: Luca Peretti <luca_peretti@hotmail.com>
License-Expression: MIT
License-File: LICENSE
Classifier: License :: OSI Approved :: MIT License
Classifier: Operating System :: OS Independent
Classifier: Programming Language :: Python :: 3
Classifier: Topic :: Scientific/Engineering :: Medical Science Apps.
Requires-Python: >=3.6
Requires-Dist: pydicom
Requires-Dist: tqdm
